<?xml version="1.0" encoding="utf-8"?>
<TablePopulationObject xmlns:xsd="http://www.w3.org/2001/XMLSchema" xmlns:xsi="http://www.w3.org/2001/XMLSchema-instance">
  <ID>query_public_activity</ID>
  <PopulationObjectName>query_public_activity</PopulationObjectName>
  <TableName>public_activity</TableName>
  <RootItemID>query_query_public_activity</RootItemID>
  <LazyDataUpdate syncMethod="Inherited" performEvery="1.00:00:00">
    <TruncateBeforeSync>false</TruncateBeforeSync>
  </LazyDataUpdate>
  <SimpleObject>true</SimpleObject>
  <IidFinderProp />
  <InputArguments>
    <Arg name="customer_id" id="queryCol_0" dataType="Integer" index="0" />
    <Arg name="activity_id" id="queryCol_1" dataType="Integer" index="1" />
    <Arg name="activity_date" id="queryCol_2" dataType="Text" index="2" />
    <Arg name="activity_note" id="queryCol_3" dataType="Text" index="3" />
  </InputArguments>
  <ItemsList>
    <Item xsi:type="DBQueryDataSave" id="query_query_public_activity" name="query_public_activity" nodeOrder="0" module="DBQuery" mapObjectModule="DBQuery" connName="CRM_DB">
      <OutputsList>
        <Output xsi:type="DBQueryDataSaveColumn" id="queryCol_0" name="customer_id" dataType="Integer" index="0" />
        <Output xsi:type="DBQueryDataSaveColumn" id="queryCol_1" name="activity_id" dataType="Integer" index="1" />
        <Output xsi:type="DBQueryDataSaveColumn" id="queryCol_2" name="activity_date" dataType="Text" index="2" />
        <Output xsi:type="DBQueryDataSaveColumn" id="queryCol_3" name="activity_note" dataType="Text" index="3" />
      </OutputsList>
      <SQL><![CDATA[SELECT * FROM public.activity]]></SQL>
    </Item>
  </ItemsList>
  <LinksList>
    <Link partId="12" fromNodeOrder="0" fromItemID="query_query_public_activity" fromColID="queryCol_0" toItemID="tbl_public_activity" toColID="tblCol_123701ee134c404f8b43f0afec2988fa" />
    <Link partId="13" fromNodeOrder="0" fromItemID="query_query_public_activity" fromColID="queryCol_1" toItemID="tbl_public_activity" toColID="tblCol_66b2297271284c869a032b17e206cce0" />
    <Link partId="14" fromNodeOrder="0" fromItemID="query_query_public_activity" fromColID="queryCol_2" toItemID="tbl_public_activity" toColID="tblCol_0847fc63e5944885b017aaf5bd136e8c" />
    <Link partId="15" fromNodeOrder="0" fromItemID="query_query_public_activity" fromColID="queryCol_3" toItemID="tbl_public_activity" toColID="tblCol_15d9ee4604dc4f849670b198eb37b442" />
  </LinksList>
  <ModeKeyColumnIDs />
  <DiagramGraph>
    <Graph name="public_activity.query_public_activity.k2tablePop.xml" lastPartID="45">
      <TableNode partID="0" name="public_activity" pos="383 5.81771469" width="253" />
      <DBQueryNode partID="7" name="CRM_DB" pos="10 0.854171753" size="253 108.291656" isRoot="true">
        <DBQuery>{"Name":"query_public_activity","ID":"query_query_public_activity","ConnName":"CRM_DB","SQL":"SELECT * FROM public.activity","ColumnsList":[{"ID":"queryCol_0","Name":"customer_id","DataType":"Integer","Index":0,"IsInputArgument":true},{"ID":"queryCol_1","Name":"activity_id","DataType":"Integer","Index":1,"IsInputArgument":true},{"ID":"queryCol_2","Name":"activity_date","DataType":"Text","Index":2,"IsInputArgument":true},{"ID":"queryCol_3","Name":"activity_note","DataType":"Text","Index":3,"IsInputArgument":true}]}</DBQuery>
      </DBQueryNode>
      <Link partID="12" from="0" to="1" pointsArr="263 36.89063 273 36.89063 313 37 333 37 373 36.85417 383 36.85417" fromNodePartID="7" fromNodeColumnName="customer_id" toNodePartID="0" toNodeColumnName="customer_id" />
      <Link partID="13" from="2" to="3" pointsArr="263 48.9635429 273 48.9635429 313 49 333 49 373 48.9270859 383 48.9270859" fromNodePartID="7" fromNodeColumnName="activity_id" toNodePartID="0" toNodeColumnName="activity_id" />
      <Link partID="14" from="4" to="5" pointsArr="263 61.0364571 273 61.0364571 313 61 333 61 373 61 383 61" fromNodePartID="7" fromNodeColumnName="activity_date" toNodePartID="0" toNodeColumnName="activity_date" />
      <Link partID="15" from="6" to="7" pointsArr="263 73.109375 273 73.109375 313 73 333 73 373 73.0729141 383 73.0729141" fromNodePartID="7" fromNodeColumnName="activity_note" toNodePartID="0" toNodeColumnName="activity_note" />
    </Graph>
  </DiagramGraph>
</TablePopulationObject>